cfgui/__init__.py
cfgui/__main__.py
cfgui/adb_handler.py
cfgui/config_manager.py
cfgui/csv_handler.py
cfgui/feature_handler.py
cfgui/game_data_getter.py
cfgui/helper.py
cfgui/item.py
cfgui/locale_handler.py
cfgui/managed_item.py
cfgui/parse_save.py
cfgui/patcher.py
cfgui/root_handler.py
cfgui/serialise_save.py
cfgui/server_handler.py
cfgui/tracker.py
cfgui/updater.py
cfgui/user_input_handler.py
cfgui/edits/__init__.py
cfgui/edits/basic/__init__.py
cfgui/edits/basic/basic_items.py
cfgui/edits/basic/catfruit.py
cfgui/edits/basic/catseyes.py
cfgui/edits/basic/ototo_base_mats.py
cfgui/edits/basic/talent_orbs.py
cfgui/edits/basic/talent_orbs_new.py
cfgui/edits/cats/__init__.py
cfgui/edits/cats/cat_helper.py
cfgui/edits/cats/cat_id_selector.py
cfgui/edits/cats/chara_drop.py
cfgui/edits/cats/clear_cat_guide.py
cfgui/edits/cats/evolve_cats.py
cfgui/edits/cats/get_remove_cats.py
cfgui/edits/cats/talents.py
cfgui/edits/cats/upgrade_blue.py
cfgui/edits/cats/upgrade_cats.py
cfgui/edits/gamototo/__init__.py
cfgui/edits/gamototo/fix_gamatoto.py
cfgui/edits/gamototo/gamatoto_xp.py
cfgui/edits/gamototo/helpers.py
cfgui/edits/gamototo/ototo_cat_cannon.py
cfgui/edits/levels/__init__.py
cfgui/edits/levels/aku.py
cfgui/edits/levels/allow_filibuster_clearing.py
cfgui/edits/levels/behemoth_culling.py
cfgui/edits/levels/clear_tutorial.py
cfgui/edits/levels/enigma_stages.py
cfgui/edits/levels/event_stages.py
cfgui/edits/levels/gauntlet.py
cfgui/edits/levels/itf_timed_scores.py
cfgui/edits/levels/legend_quest.py
cfgui/edits/levels/main_story.py
cfgui/edits/levels/outbreaks.py
cfgui/edits/levels/story_level_id_selector.py
cfgui/edits/levels/towers.py
cfgui/edits/levels/treasures.py
cfgui/edits/levels/uncanny.py
cfgui/edits/levels/unlock_aku_realm.py
cfgui/edits/other/__init__.py
cfgui/edits/other/cat_shrine.py
cfgui/edits/other/claim_user_rank_rewards.py
cfgui/edits/other/create_new_account.py
cfgui/edits/other/fix_elsewhere.py
cfgui/edits/other/fix_time_issues.py
cfgui-0.0.5.dist-info/METADATA
cfgui-0.0.5.dist-info/WHEEL
cfgui-0.0.5.dist-info/top_level.txt
cfgui-0.0.5.dist-info/RECORD
